a3m/__init__.py
a3m/appconfig.py
a3m/archivematicaFunctions.py
a3m/bag.py
a3m/common_metrics.py
a3m/countryCodes.py
a3m/databaseFunctions.py
a3m/dicts.py
a3m/executeOrRunSubProcess.py
a3m/fileOperations.py
a3m/namespaces.py
a3m/api/transferservice/v1beta1/__init__.py
a3m/api/transferservice/v1beta1/request_response_pb2.py
a3m/api/transferservice/v1beta1/request_response_pb2.pyi
a3m/api/transferservice/v1beta1/request_response_pb2_grpc.py
a3m/api/transferservice/v1beta1/service_pb2.py
a3m/api/transferservice/v1beta1/service_pb2.pyi
a3m/api/transferservice/v1beta1/service_pb2_grpc.py
a3m/assets/workflow-schema-v1.json
a3m/assets/workflow.json
a3m/cli/__init__.py
a3m/cli/common.py
a3m/cli/client/__init__.py
a3m/cli/client/__main__.py
a3m/cli/client/wrapper.py
a3m/cli/server/__init__.py
a3m/cli/server/__main__.py
a3m/client/__init__.py
a3m/client/job.py
a3m/client/mcp.py
a3m/client/metrics.py
a3m/client/assets/README/README.html
a3m/client/assets/catalog/catalog.xml
a3m/client/assets/mets/mets.xsd
a3m/client/assets/mets/xlink.xsd
a3m/client/assets/mods/mods.xsd
a3m/client/assets/mods/xml.xsd
a3m/client/assets/premis/premis-v2-2.xsd
a3m/client/assets/premis/premis.xsd
a3m/client/clientScripts/__init__.py
a3m/client/clientScripts/a3m_download_transfer.py
a3m/client/clientScripts/a3m_store_aip.py
a3m/client/clientScripts/archivematicaCreateMETSMetadataCSV.py
a3m/client/clientScripts/archivematicaCreateMETSRights.py
a3m/client/clientScripts/assign_file_uuids.py
a3m/client/clientScripts/assign_uuids_to_directories.py
a3m/client/clientScripts/bag_with_empty_directories.py
a3m/client/clientScripts/change_names.py
a3m/client/clientScripts/change_object_names.py
a3m/client/clientScripts/characterize_file.py
a3m/client/clientScripts/check_for_service_directory.py
a3m/client/clientScripts/check_for_submission_documentation.py
a3m/client/clientScripts/check_transfer_directory_for_objects.py
a3m/client/clientScripts/cmd_chmod.py
a3m/client/clientScripts/cmd_cp.py
a3m-0.8.1.dist-info/METADATA
a3m-0.8.1.dist-info/WHEEL
a3m-0.8.1.dist-info/entry_points.txt
a3m-0.8.1.dist-info/licenses/LICENSE
a3m-0.8.1.dist-info/RECORD
