Metadata-Version: 2.3
Name: a3m
Version: 0.8.1
Summary: Lightweight Archivematica
Project-URL: homepage, https://github.com/artefactual-labs/a3m
Project-URL: documentation, https://a3m.readthedocs.io/
Project-URL: repository, https://github.com/artefactual-labs/a3m
Project-URL: issues, https://github.com/artefactual-labs/a3m/issues
Author-email: "Artefactual Systems Inc." <info@artefactual.com>
Maintainer-email: "Artefactual Systems Inc." <info@artefactual.com>
License:                     GNU AFFERO GENERAL PUBLIC LICENSE
License-File: LICENSE
Keywords: archivematica,preservation
Classifier: Development Status :: 1 - Planning
Classifier: Environment :: Console
Classifier: Intended Audience :: Information Technology
Classifier: License :: OSI Approved :: GNU Affero General Public License v3
Classifier: Operating System :: POSIX :: Linux
Classifier: Programming Language :: Python
Classifier: Programming Language :: Python :: 3 :: Only
Classifier: Programming Language :: Python :: 3.12
Classifier: Topic :: System :: Archiving
Classifier: Topic :: System :: Archiving :: Backup
Classifier: Topic :: System :: Archiving :: Compression
Classifier: Topic :: System :: Archiving :: Mirroring
Classifier: Topic :: System :: Archiving :: Packaging
Requires-Python: >=3.12
Requires-Dist: ammcpc~=0.1
Requires-Dist: bagit
Requires-Dist: boto3~=1.28
Requires-Dist: click~=8.1
Requires-Dist: django-stubs-ext~=4.2
Requires-Dist: django~=4.2
Requires-Dist: googleapis-common-protos~=1.61
Requires-Dist: grpcio-reflection~=1.59
Requires-Dist: grpcio-status~=1.59
Requires-Dist: grpcio~=1.59
Requires-Dist: jsonschema~=4.19
Requires-Dist: lxml~=4.9
Requires-Dist: metsrw~=0.4
Requires-Dist: platformdirs~=4.1
Requires-Dist: prometheus-client~=0.17
Requires-Dist: pygfried~=0.6
Requires-Dist: requests~=2.31
Requires-Dist: rich~=13.6
Requires-Dist: tenacity~=8.2
Requires-Dist: unidecode~=1.3
